tpucare/__init__.py
tpucare-0.5.0.dist-info/LICENSE
tpucare-0.5.0.dist-info/METADATA
tpucare-0.5.0.dist-info/WHEEL
tpucare-0.5.0.dist-info/top_level.txt
tpucare-0.5.0.dist-info/RECORD
