Metadata-Version: 2.1
Name: tpucare
Version: 0.5.0
Summary: Automatically take good care of your preemptible TPUs
Home-page: https://github.com/clashluke/tpucare
Author: Lucas Nestler
Author-email: github.tpucare@nestler.sh
License: BSD
Platform: UNKNOWN
Classifier: Development Status :: 5 - Production/Stable
Classifier: License :: OSI Approved :: BSD License
Classifier: Programming Language :: Python
Classifier: Programming Language :: Python :: 3.7
Classifier: Programming Language :: Python :: 3.8
Classifier: Programming Language :: Python :: 3.9
Classifier: Topic :: Software Development :: Libraries
Classifier: Topic :: Software Development :: Libraries :: Python Modules
Classifier: Intended Audience :: Developers
Requires-Python: >=3.7
License-File: LICENSE
